fits_align/__init__.py
fits_align/align.py
fits_align/ident.py
fits_align/imgcat.py
fits_align/quad.py
fits_align/star.py
fits_align/utils.py
fits_align-0.4.4.dist-info/LICENSE.txt
fits_align-0.4.4.dist-info/METADATA
fits_align-0.4.4.dist-info/WHEEL
fits_align-0.4.4.dist-info/top_level.txt
fits_align-0.4.4.dist-info/RECORD
