Metadata-Version: 2.1
Name: fits_align
Version: 0.4.4
Summary: Align a sequence of astronomical FITS files based on sources extracted in each image. The aligned files will be geometrically reprojected so all the images are the same size and shape.
Author: Edward Gomez
Classifier: Development Status :: 5 - Production/Stable
Classifier: License :: OSI Approved :: GNU General Public License v3 (GPLv3)
Classifier: Topic :: Software Development :: Build Tools
Classifier: Programming Language :: Python :: 2.7
Classifier: Programming Language :: Python :: 3
Classifier: Programming Language :: Python :: 3.4
Classifier: Programming Language :: Python :: 3.6
Classifier: Programming Language :: Python :: 3.7
License-File: LICENSE.txt
Requires-Dist: astropy
Requires-Dist: numpy
Requires-Dist: pillow
